spop/__init__.py
spop/symbol/__init__.py
spop/symbol/_test.py
spop-0.0.0.dist-info/METADATA
spop-0.0.0.dist-info/WHEEL
spop-0.0.0.dist-info/RECORD
