Metadata-Version: 2.3
Name: spop
Version: 0.0.0
Summary: Add your description here
Author-email: Movpasd <54367524+movpasd@users.noreply.github.com>
Requires-Python: >=3.12
Requires-Dist: numpy>=2.1.2
Provides-Extra: highs
Requires-Dist: highspy>=1.8.0; extra == 'highs'
